lamin_vault/__init__.py
lamin_vault/client/__init__.py
lamin_vault/client/_create_vault_client.py
lamin_vault/client/_init_instance_vault.py
lamin_vault/client/_set_collaborator_role.py
lamin_vault/client/postgres/__init__.py
lamin_vault/client/postgres/_connection_config_db_exists.py
lamin_vault/client/postgres/_create_or_update_connection_config_db.py
lamin_vault/client/postgres/_create_or_update_role_and_policy_db.py
lamin_vault/client/postgres/_delete_db_role.py
lamin_vault/client/postgres/_delete_db_vault.py
lamin_vault/client/postgres/_get_db_from_vault.py
lamin_vault/client/postgres/_role_and_policy_exist.py
lamin_vault/client/postgres/_set_db_role.py
lamin_vault/server/__init__.py
lamin_vault/server/_create_instance_admin_token_from_jwt.py
lamin_vault/server/_create_token_from_jwt.py
lamin_vault/server/_get_vault_client_approle.py
lamin_vault/utils/__init__.py
lamin_vault/utils/_lamin_dsn.py
lamin_vault/utils/_supabase_client.py
lamin_vault/utils/connector.py
lamin_vault/utils/extract_access_token.py
lamin_vault-0.1.2.dist-info/WHEEL
lamin_vault-0.1.2.dist-info/METADATA
lamin_vault-0.1.2.dist-info/RECORD
