Metadata-Version: 2.1
Name: lamin_vault
Version: 0.1.2
Summary: Lamin vault.
Author-email: Lamin Labs <open-source@lamin.ai>
Requires-Dist: hvac[parser]
Requires-Dist: psycopg2-binary
Requires-Dist: supabase
Requires-Dist: pyjwt
Requires-Dist: pydantic[dotenv]
Requires-Dist: pre-commit ; extra == "dev"
Requires-Dist: nox ; extra == "dev"
Requires-Dist: pytest>=6.0 ; extra == "dev"
Requires-Dist: pytest-cov ; extra == "dev"
Requires-Dist: nbproject_test ; extra == "dev"
Requires-Dist: lamindb_setup ; extra == "dev"
Requires-Dist: s3fs ; extra == "dev"
Requires-Dist: sqlalchemy ; extra == "dev"
Requires-Dist: laminhub_rest ; extra == "dev"
Requires-Dist: pandas ; extra == "dev"
Project-URL: Home, https://github.com/laminlabs/lamin-vault
Provides-Extra: dev
